writecode/__init__.py
writecode/main.py
writecode-0.1.3.dist-info/METADATA
writecode-0.1.3.dist-info/WHEEL
writecode-0.1.3.dist-info/top_level.txt
writecode-0.1.3.dist-info/RECORD
