Metadata-Version: 2.1
Name: writecode
Version: 0.1.3
Summary: Write code using OpenAI's Codex model
Home-page: https://github.com/supervised/codeit
License: UNKNOWN
Platform: UNKNOWN
Classifier: Programming Language :: Python :: 3
Classifier: License :: OSI Approved :: MIT License
Classifier: Operating System :: OS Independent
Requires-Python: >=3.6
